LICENSE.txt
README.md
setup.py
rocket_mahdi/rocket.py
rocket_mahdi.egg-info/PKG-INFO
rocket_mahdi.egg-info/SOURCES.txt
rocket_mahdi.egg-info/dependency_links.txt
rocket_mahdi.egg-info/requires.txt
rocket_mahdi.egg-info/top_level.txt