Metadata-Version: 2.1
Name: rocket-mahdi
Version: 1.0.0
Summary: An awesome package that does something
Home-page: http://pypi.python.org/pypi/<rocket_mahdi>/
Author: mahdi
Author-email: am.tahir@esi-sba.dz
License: LICENSE.txt
License-File: LICENSE.txt
